recursive_regex/__init__.py
recursive_regex/recursive_regex.py
recursive_regex/sample_config.py
recursive_regex-0.1.1.dist-info/LICENSE
recursive_regex-0.1.1.dist-info/METADATA
recursive_regex-0.1.1.dist-info/WHEEL
recursive_regex-0.1.1.dist-info/entry_points.txt
recursive_regex-0.1.1.dist-info/top_level.txt
recursive_regex-0.1.1.dist-info/RECORD
