Metadata-Version: 2.1
Name: recursive-regex
Version: 0.1.1
Summary: Search and substitute an regular expresion recursively in a directory.
Home-page: https://github.com/isidroas/recursive_regex
Author: Isidro Arias
Author-email: isidroariass@hotmail.es
License: UNKNOWN
Project-URL: Bug Tracker, https://github.com/isidroas/recursive_regex/issues
Platform: UNKNOWN
Classifier: Programming Language :: Python :: 3
Classifier: License :: OSI Approved :: MIT License
Classifier: Operating System :: OS Independent
Requires-Python: >=3.6
License-File: LICENSE
Requires-Dist: PyYAML (==5.*)
